theme/__init__.py
theme/apps.py
theme/context_processors.py
theme/models.py
theme/tests.py
theme/urls.py
theme/views.py
theme/migrations/0001_initial.py
theme/migrations/__init__.py
django_theme-0.3.dist-info/LICENSE
django_theme-0.3.dist-info/METADATA
django_theme-0.3.dist-info/WHEEL
django_theme-0.3.dist-info/top_level.txt
django_theme-0.3.dist-info/RECORD
